tensorscout/__init__.py
tensorscout/main.py
tensorscout-2.3.0.dist-info/METADATA
tensorscout-2.3.0.dist-info/WHEEL
tensorscout-2.3.0.dist-info/LICENSE
tensorscout-2.3.0.dist-info/RECORD
