Metadata-Version: 2.1
Name: tensorscout
Version: 2.3.0
Summary: A Python library for tensor operations powered by parallel processing
License: MIT
Author: andrewrgarcia
Author-email: garcia.gtr@gmail.com
Requires-Python: >=3.8,<3.12
Classifier: License :: OSI Approved :: MIT License
Classifier: Programming Language :: Python :: 3
Classifier: Programming Language :: Python :: 3.8
Classifier: Programming Language :: Python :: 3.9
Classifier: Programming Language :: Python :: 3.10
Classifier: Programming Language :: Python :: 3.11
Requires-Dist: matplotlib (>=3.7.1,<4.0.0)
Requires-Dist: numpy (>=1.24.2,<2.0.0)
Requires-Dist: pathos (>=0.3.0,<0.4.0)
Requires-Dist: scipy (>=1.10.1,<2.0.0)
Requires-Dist: timethis (>=0.1.1,<0.2.0)
